AUTHORS.rst
CHANGELOG.rst
LICENSE
MANIFEST.in
README.rst
setup.py
django_layers_hr.egg-info/PKG-INFO
django_layers_hr.egg-info/SOURCES.txt
django_layers_hr.egg-info/dependency_links.txt
django_layers_hr.egg-info/not-zip-safe
django_layers_hr.egg-info/requires.txt
django_layers_hr.egg-info/top_level.txt
layers/__init__.py
layers/apps.py
layers/decorators.py
layers/finders.py
layers/models.py
layers/monkey.py
layers/loaders/__init__.py
layers/loaders/app_directories.py
layers/loaders/filesystem.py
layers/management/__init__.py
layers/management/commands/__init__.py
layers/management/commands/layers_collectstatic.py
layers/management/commands/load_layers.py
layers/migrations/0001_initial.py
layers/migrations/0002_auto_20161219_1041.py
layers/migrations/__init__.py
layers/templates/layers/exclude_from_layers.html
layers/tests/README.txt
layers/tests/__init__.py
layers/tests/manage.py
layers/tests/models.py
layers/tests/test_decorators.py
layers/tests/test_layers.py
layers/tests/test_legacy.py
layers/tests/test_management_commands.py
layers/tests/urls.py
layers/tests/views.py
layers/tests/requirements/110.txt
layers/tests/requirements/111.txt
layers/tests/requirements/19.txt
layers/tests/settings/110.py
layers/tests/settings/111.py
layers/tests/settings/19.py
layers/tests/settings/__init__.py
layers/tests/someapp/__init__.py
layers/tests/someapp/models.py
layers/tests/someapp/static/basic/someapp/bar.css
layers/tests/someapp/static/basic/someapp/foo.css
layers/tests/someapp/static/someapp/plain.css
layers/tests/someapp/static/web/someapp/bar.css
layers/tests/someapp/templates/basic/someapp/bar.html
layers/tests/someapp/templates/basic/someapp/basic_override_me.html
layers/tests/someapp/templates/basic/someapp/basic_override_me_in_another_app.html
layers/tests/someapp/templates/basic/someapp/foo.html
layers/tests/someapp/templates/someapp/plain.html
layers/tests/someapp/templates/someapp/plain_override_me.html
layers/tests/someapp/templates/web/someapp/bar.html
layers/tests/someapp/templates/web/someapp/basic_override_me.html
layers/tests/someapp/templates/web/someapp/plain_override_me.html
layers/tests/static/basic/tests/bar.css
layers/tests/static/basic/tests/basic.css
