Metadata-Version: 1.1
Name: django-layers-hr
Version: 1.11.1
Summary: Serve different templates and static files for eg. mobi and web. Layers can be stacked to enable resource re-use.
Home-page: http://github.com/hedleyroos/django-layers
Author: Hedley Roos
Author-email: hedleyroos@gmail.com
License: BSD
Platform: UNKNOWN
Classifier: Programming Language :: Python
Classifier: License :: OSI Approved :: BSD License
Classifier: Development Status :: 4 - Beta
Classifier: Operating System :: OS Independent
Classifier: Framework :: Django
Classifier: Intended Audience :: Developers
Classifier: Topic :: Internet :: WWW/HTTP :: Dynamic Content
